MANIFEST.in
README.md
requirements.txt
setup.py
gimp/__init__.py
gimp/plugins/__init__.py
gimp/plugins/console/__init__.py
gimp/plugins/console/console
gimp/plugins/console/main.py
gimp/plugins/console/utils.py
gimp/plugins/console/gtk/__init__.py
gimp/plugins/console/gtk/gtkmatplotlibshell.py
gimp/plugins/console/gtk/gtkpyinterpreter.py
gimp/plugins/console/gtk/pyconsole.py
gimp_console.egg-info/PKG-INFO
gimp_console.egg-info/SOURCES.txt
gimp_console.egg-info/dependency_links.txt
gimp_console.egg-info/requires.txt
gimp_console.egg-info/top_level.txt