Metadata-Version: 2.1
Name: gimp-console
Version: 0.2.0
Summary: A GTK Python Console for the GIMP python environment
Home-page: https://github.com/isman7/gimp-python-development/
Author: ibenito
Author-email: ismaelbenito@protonmail.com
License: GNU GPLv3
Platform: UNKNOWN
